{
    "name"      : "Christmas",
    "id"        : "0",
    "masterId"  : "255",
    "events"    : [
        {
            "id"            :   "1",
            "name"          :   "start_game",
            "device_id"     :   "11",
            "event"         :   "toggle",
            "eventType"     :   "button",
            "data"          :   "1",
            "description"   :   "the beginning of the game, code typed or something",
            "dependencies"  :   [],
            "actions"       :   ["chest_door_start"],
            "message"       :   "started the game",
            "state"         :   "start_game"
        },
        {
            "id"            :   "9",
            "name"          :   "keypad1",
            "device_id"     :   "13",
            "event"         :   "code",
            "eventType"     :   "keypad",
            "data"          :   "111111",
            "description"   :   "Open Chest Door",
            "dependencies"  :   [],
            "actions"       :   ["relay1 on"],
            "can_toggle"    :   "true",
            "message"       :   "opened chest",
            "state"         :   "chest_opened"
        },
        {
            "id"            :   "9",
            "name"          :   "keypad1",
            "device_id"     :   "13",
            "event"         :   "code",
            "eventType"     :   "keypad",
            "data"          :   "222222",
            "description"   :   "Open Chest Door",
            "dependencies"  :   [],
            "actions"       :   ["relay2 on"],
            "can_toggle"    :   "true",
            "message"       :   "opened chest",
            "state"         :   "chest_opened"
        },
        {
            "id"            :   "9",
            "name"          :   "keypad1",
            "device_id"     :   "13",
            "event"         :   "code",
            "eventType"     :   "keypad",
            "data"          :   "333333",
            "description"   :   "Open Chest Door",
            "dependencies"  :   [],
            "actions"       :   ["relay3 on"],
            "can_toggle"    :   "true",
            "message"       :   "opened chest",
            "state"         :   "chest_opened"
        },
        {
            "id"            :   "9",
            "name"          :   "keypad1",
            "device_id"     :   "13",
            "event"         :   "code",
            "eventType"     :   "keypad",
            "data"          :   "444444",
            "description"   :   "Open Chest Door",
            "dependencies"  :   [],
            "actions"       :   ["relay1 off"],
            "can_toggle"    :   "true",
            "message"       :   "opened chest",
            "state"         :   "chest_opened"
        },
        {
            "id"            :   "9",
            "name"          :   "keypad1",
            "device_id"     :   "13",
            "event"         :   "code",
            "eventType"     :   "keypad",
            "data"          :   "555555",
            "description"   :   "Open Chest Door",
            "dependencies"  :   [],
            "actions"       :   ["relay2 off"],
            "can_toggle"    :   "true",
            "message"       :   "opened chest",
            "state"         :   "chest_opened"
        },
        {
            "id"            :   "9",
            "name"          :   "keypad1",
            "device_id"     :   "13",
            "event"         :   "code",
            "eventType"     :   "keypad",
            "data"          :   "666666",
            "description"   :   "Open Chest Door",
            "dependencies"  :   [],
            "actions"       :   ["relay3 off"],
            "can_toggle"    :   "true",
            "message"       :   "opened chest",
            "state"         :   "chest_opened"
        },
        {
            "id"            :   "10",
            "name"          :   "tetris",
            "device_id"     :   "25",
            "event"         :   "toggle",
            "eventType"     :   "magnetSwitch",
            "data"          :   [1,1,1,1,1,1,1,1,1,1],
            "description"   :   "tetris0",
            "dependencies"  :   [],
            "actions"       :   ["top_drawer_toggle"],
            "can_toggle"    :   "true",
            "message"       :   "Tetris",
            "state"         :   "tetris"
        }
    ],
    "actions"   : [
        {
            "id"            :   "14",
            "name"          :   "relay1 on",
            "device_id"     :   "12",
            "event"         :   "noneE",
            "eventType"     :   "noneET",
            "wait"          :   0,
            "action"        :   "start",
            "actionType"    :   "relay",
            "data"          :   "15",
            "description"   :   "Chest Door On",
            "repeatable"    :   "true",
            "dependencies"  :   [],
            "actions"       :   [],
            "message"       :   "chest_door_on",
            "state"         :   "test_led_off"
        },
        {
            "id"            :   "14",
            "name"          :   "relay2 on",
            "device_id"     :   "12",
            "event"         :   "noneE",
            "eventType"     :   "noneET",
            "wait"          :   0,
            "action"        :   "start",
            "actionType"    :   "relay",
            "data"          :   "2",
            "description"   :   "Chest Door On",
            "repeatable"    :   "true",
            "dependencies"  :   [],
            "actions"       :   [],
            "message"       :   "chest_door_on",
            "state"         :   "test_led_off"
        },
        {
            "id"            :   "14",
            "name"          :   "relay3 on",
            "device_id"     :   "12",
            "event"         :   "noneE",
            "eventType"     :   "noneET",
            "wait"          :   0,
            "action"        :   "start",
            "actionType"    :   "relay",
            "data"          :   "4",
            "description"   :   "Chest Door On",
            "repeatable"    :   "true",
            "dependencies"  :   [],
            "actions"       :   [],
            "message"       :   "chest_door_on",
            "state"         :   "test_led_off"
        },
        {
            "id"            :   "14",
            "name"          :   "relay1 off",
            "device_id"     :   "12",
            "event"         :   "noneE",
            "eventType"     :   "noneET",
            "wait"          :   0,
            "action"        :   "stop",
            "actionType"    :   "relay",
            "data"          :   "15",
            "description"   :   "Chest Door On",
            "repeatable"    :   "true",
            "dependencies"  :   [],
            "actions"       :   [],
            "message"       :   "chest_door_on",
            "state"         :   "test_led_off"
        },
        {
            "id"            :   "14",
            "name"          :   "relay2 off",
            "device_id"     :   "12",
            "event"         :   "noneE",
            "eventType"     :   "noneET",
            "wait"          :   0,
            "action"        :   "stop",
            "actionType"    :   "relay",
            "data"          :   "2",
            "description"   :   "Chest Door On",
            "repeatable"    :   "true",
            "dependencies"  :   [],
            "actions"       :   [],
            "message"       :   "chest_door_on",
            "state"         :   "test_led_off"
        },
        {
            "id"            :   "14",
            "name"          :   "relay3 off",
            "device_id"     :   "12",
            "event"         :   "noneE",
            "eventType"     :   "noneET",
            "wait"          :   0,
            "action"        :   "stop",
            "actionType"    :   "relay",
            "data"          :   "4",
            "description"   :   "Chest Door On",
            "repeatable"    :   "true",
            "dependencies"  :   [],
            "actions"       :   [],
            "message"       :   "chest_door_on",
            "state"         :   "test_led_off"
        }
    ]
}